settngs/__init__.py
settngs/__main__.py
settngs/py.typed
settngs-0.11.1.dist-info/licenses/LICENSE
settngs-0.11.1.dist-info/METADATA
settngs-0.11.1.dist-info/WHEEL
settngs-0.11.1.dist-info/top_level.txt
settngs-0.11.1.dist-info/RECORD
