Metadata-Version: 2.4
Name: settngs
Version: 0.11.1
Summary: A library for managing settings
Home-page: https://github.com/lordwelch/settngs
Author: Timmy Welch
Author-email: timmy@narnian.us
License: MIT
Classifier: Programming Language :: Python :: 3
Classifier: Programming Language :: Python :: 3 :: Only
Classifier: Programming Language :: Python :: Implementation :: CPython
Classifier: Programming Language :: Python :: Implementation :: PyPy
Requires-Python: >=3.9
License-File: LICENSE
Requires-Dist: typing-extensions>=4.3.0; python_version < "3.11"
Dynamic: license-file
